{
    "diwakar": {
        "email_address": "asd@gmail.com",
        "dev_token": "NvcZya59MafJucxkbX6Tbvju",
        "med_token": "2c28b226193844ab1e30e0dd607eb185825162b31c2f3ef00d2eadb743037a456",
        "hashnode_key": "48f68fbd-9249-4ed4-b8b4-c9b6c983540b",
        "substack_email": "hidevscommunity@gmail.com",
        "substack_password": "B&z6!&2@Nj&g?Hi",
        "substack_publication_url": "https://hidevscommunity.substack.com",
        "substack_user_id": "134253096",
        "hashnode_publication_id": "6538acb0b0f75b67cacf1f96",
        "password": "123123123"
    }
}